{
    "total_sessions": 164,
    "lifetime_profit": 16497,
    "total_items": 356,
    "max_profit": 650,
    "max_items": 5,
    "playstyle_counts": {
        "The Strategist": 40,
        "The Value Hunter": 42,
        "The Bully": 30,
        "The Sniper": 26,
        "The Gambler": 20,
        "The Hesitator": 2,
        "The Machine": 2,
        "The Tactician": 1,
        "Absentee": 1
    },
    "playstyle_wins": {
        "The Strategist": 100,
        "The Value Hunter": 66,
        "The Bully": 120,
        "The Sniper": 24,
        "The Gambler": 40,
        "The Hesitator": 1,
        "The Machine": 5,
        "The Tactician": 0,
        "Absentee": 0
    },
    "playstyle_profits": {
        "The Strategist": 10000,
        "The Value Hunter": 2050,
        "The Bully": -1500,
        "The Sniper": 5888,
        "The Gambler": 200,
        "The Hesitator": -45,
        "The Machine": -96,
        "The Tactician": 0,
        "Absentee": 0
    },
    "playstyle_spent": {
        "The Strategist": 40000,
        "The Value Hunter": 15905,
        "The Bully": 60000,
        "The Sniper": 12498,
        "The Gambler": 24000,
        "The Hesitator": 85,
        "The Machine": 688,
        "The Tactician": 0,
        "Absentee": 0
    },
    "playstyle_successes": {
        "The Strategist": 32,
        "The Value Hunter": 31,
        "The Bully": 6,
        "The Sniper": 15,
        "The Gambler": 8
    }
}